{
    "shoot_on_an_angle_activity::intro_card_0::headline": "تمرین عکاسی از زاویه‌های مختلف",
    "shoot_on_an_angle_activity::text_card_0::text": "حالا که درس عکاسی از زاویه‌های مختلف را آموخته‌اید، این درس به شما کمک می‌کند که بیشتر تمرین کنید. زاویه‌های مختلفی را با سوژه‌های مختلف امتحان کنید.",
    "shoot_on_an_angle_activity::link_card_2::text": "درس قبل",
    "shoot_on_an_angle_activity::title": "تمرین عکاسی از زاویه‌های مختلف",
    "shoot_on_an_angle_activity::clip_card_0::goals[0]": "زاویه‌های خاص را امتحان کنید؛ نه فقط زاویه بالا یا پایین.",
    "shoot_on_an_angle_activity::intro_card_0::level": "مقدمه ۱",
    "shoot_on_an_angle_activity::link_card_0::text": "بازگشت به درس",
    "shoot_on_an_angle_activity::link_card_1::text": "درس بعدی"
}