{
    "title": "Was ist die wichtigste Sache, die du gelernt hast?", 
    "storyPathTemplateFiles": {
        "g_odvw_4": "g_odvw_4.json"
    }, 
    "dependencies": [
        {
            "dependencyId": "g_odvw_4", 
            "dependencyFile": "g_odvw_4.json"
        }
    ], 
    "classPackage": "scal.io.liger.model", 
    "cards": [
        {
            "action": "LOAD", 
            "type": "LoaderHeadlessCard", 
            "id": "loader_card", 
            "target": "g_odvw_4"
        }
    ], 
    "currentStoryPathFile": "g_odvw_4.json", 
    "id": "g_odvw_4_library"
}